{
  "fixture": {
    "id": 1208745,
    "referee": "Mario Melero",
    "timezone": "UTC",
    "date": "2025-03-14T20:00:00+00:00",
    "timestamp": 1741982400,
    "periods": {
      "first": 1741982400,
      "second": 1741986000
    },
    "venue": {
      "id": 1481,
      "name": "Estadio de Gran Canaria",
      "city": "Las Palmas de Gran Canaria"
    },
    "status": {
      "long": "Match Finished",
      "short": "FT",
      "elapsed": 90,
      "extra": 10
    }
  },
  "league": {
    "id": 140,
    "name": "La Liga",
    "country": "Spain",
    "logo": "https://media.api-sports.io/football/leagues/140.png",
    "flag": "https://media.api-sports.io/flags/es.svg",
    "season": 2024,
    "round": "Regular Season - 28",
    "standings": true
  },
  "teams": {
    "home": {
      "id": 534,
      "name": "Las Palmas",
      "logo": "https://media.api-sports.io/football/teams/534.png",
      "winner": null
    },
    "away": {
      "id": 542,
      "name": "Alaves",
      "logo": "https://media.api-sports.io/football/teams/542.png",
      "winner": null
    }
  },
  "goals": {
    "home": 2,
    "away": 2
  },
  "score": {
    "halftime": {
      "home": 0,
      "away": 1
    },
    "fulltime": {
      "home": 2,
      "away": 2
    },
    "extratime": {
      "home": null,
      "away": null
    },
    "penalty": {
      "home": null,
      "away": null
    }
  }
}