{
  "fixture": {
    "id": 1208522,
    "referee": "Isidro Díaz de Mera",
    "timezone": "UTC",
    "date": "2024-08-31T15:00:00+00:00",
    "timestamp": 1725116400,
    "periods": {
      "first": 1725116400,
      "second": 1725120000
    },
    "venue": {
      "id": 19939,
      "name": "Estadi Olímpic Lluís Companys",
      "city": "Barcelona"
    },
    "status": {
      "long": "Match Finished",
      "short": "FT",
      "elapsed": 90,
      "extra": null
    }
  },
  "league": {
    "id": 140,
    "name": "La Liga",
    "country": "Spain",
    "logo": "https://media.api-sports.io/football/leagues/140.png",
    "flag": "https://media.api-sports.io/flags/es.svg",
    "season": 2024,
    "round": "Regular Season - 4",
    "standings": true
  },
  "teams": {
    "home": {
      "id": 529,
      "name": "Barcelona",
      "logo": "https://media.api-sports.io/football/teams/529.png",
      "winner": true
    },
    "away": {
      "id": 720,
      "name": "Valladolid",
      "logo": "https://media.api-sports.io/football/teams/720.png",
      "winner": false
    }
  },
  "goals": {
    "home": 7,
    "away": 0
  },
  "score": {
    "halftime": {
      "home": 3,
      "away": 0
    },
    "fulltime": {
      "home": 7,
      "away": 0
    },
    "extratime": {
      "home": null,
      "away": null
    },
    "penalty": {
      "home": null,
      "away": null
    }
  }
}